logrus/__init__.py
logrus/_core.py
logrus/py.typed
logrus/pytest_plugin.py
bolton_logrus-0.1.3.dist-info/METADATA
bolton_logrus-0.1.3.dist-info/WHEEL
bolton_logrus-0.1.3.dist-info/top_level.txt
bolton_logrus-0.1.3.dist-info/RECORD
