Metadata-Version: 2.1
Name: bolton-logrus
Version: 0.1.3
Summary: Better logging made easy with support for structlog and the standard logging module.
Home-page: https://github.com/python-boltons/logrus
Author: Bryan M Bugyi
Author-email: bryanbugyi34@gmail.com
License: MIT license
Classifier: Development Status :: 3 - Alpha
Classifier: Intended Audience :: Developers
Classifier: License :: OSI Approved :: MIT License
Classifier: Natural Language :: English
Classifier: Programming Language :: Python :: 3
Classifier: Programming Language :: Python :: 3.8
Classifier: Programming Language :: Python :: 3.9
Classifier: Programming Language :: Python :: 3.10
Requires-Python: >=3.8
Requires-Dist: bolton-metaman ~=0.1.1
Requires-Dist: structlog >=24
